<?xml version="1.0" encoding="utf-8" ?>
<dwsync>
<file name="TSUBACHA_logo1.png" server="ftp.88154f88faf2aaa2.main.jp" local="131156329333325317" remote="130890492000000000" Dst="0" />
<file name="TSUBACHA_logo2.png" server="ftp.88154f88faf2aaa2.main.jp" local="131156329339229343" remote="130890492000000000" Dst="0" />
<file name="TSUBACHA_logo3.png" server="ftp.88154f88faf2aaa2.main.jp" local="131156329340309362" remote="130890492000000000" Dst="0" />
<file name="TSUBACHA_logo4.png" server="ftp.88154f88faf2aaa2.main.jp" local="131156329340715010" remote="130890492000000000" Dst="0" />
<file name="TSUBACHA_logo5.png" server="ftp.88154f88faf2aaa2.main.jp" local="131156329344259590" remote="130890492000000000" Dst="0" />
<file name="TSUBACHAイチゴロゴ分割1.png" server="ftp.88154f88faf2aaa2.main.jp" local="131156329345059617" remote="130890492000000000" Dst="0" />
<file name="TSUBACHAイチゴロゴ分割2.png" server="ftp.88154f88faf2aaa2.main.jp" local="131156329345099619" remote="130890492000000000" Dst="0" />
<file name="TSUBACHAイチゴロゴ分割3.png" server="ftp.88154f88faf2aaa2.main.jp" local="131156329349705265" remote="130890492000000000" Dst="0" />
<file name="TSUBACHAイチゴロゴ分割4.png" server="ftp.88154f88faf2aaa2.main.jp" local="131156329349705265" remote="130890492000000000" Dst="0" />
<file name="back1.gif" server="ftp.88154f88faf2aaa2.main.jp" local="131156329349705265" remote="130709916000000000" Dst="0" />
<file name="instagram1.gif" server="ftp.88154f88faf2aaa2.main.jp" local="131156329365760336" remote="130709916000000000" Dst="0" />
<file name="tsubacha_logobase.png" server="ftp.88154f88faf2aaa2.main.jp" local="131156329422208707" remote="130872348000000000" Dst="0" />
<file name="tsubacha_t_logoon.png" server="ftp.88154f88faf2aaa2.main.jp" local="131156329427784852" remote="130872348000000000" Dst="0" />
<file name="tsubacha_logobase_on.png" server="ftp.88154f88faf2aaa2.main.jp" local="131156329429463040" remote="130890492000000000" Dst="0" />
<file name="tsubacha_t_logo.png" server="ftp.88154f88faf2aaa2.main.jp" local="131156329429463040" remote="130872348000000000" Dst="0" />
<file name="twitter1-610x169.gif" server="ftp.88154f88faf2aaa2.main.jp" local="131156329434112629" remote="130709916000000000" Dst="0" />
<file name="tsubacha_top600.png" server="ftp.88154f88faf2aaa2.main.jp" local="131156329434803123" remote="130709916000000000" Dst="0" />
</dwsync>